alobj.cp311-win_amd64.pyd
gisobj.cp311-win_amd64.pyd
gisobj-0.0.1.dist-info/METADATA
gisobj-0.0.1.dist-info/WHEEL
gisobj-0.0.1.dist-info/top_level.txt
gisobj-0.0.1.dist-info/RECORD
